google/adk/__init__.py
google/adk/py.typed
google/adk/runners.py
google/adk/version.py
google/adk/a2a/__init__.py
google/adk/a2a/experimental.py
google/adk/a2a/converters/__init__.py
google/adk/a2a/converters/event_converter.py
google/adk/a2a/converters/part_converter.py
google/adk/a2a/converters/request_converter.py
google/adk/a2a/converters/utils.py
google/adk/a2a/executor/__init__.py
google/adk/a2a/executor/a2a_agent_executor.py
google/adk/a2a/executor/task_result_aggregator.py
google/adk/a2a/logs/__init__.py
google/adk/a2a/logs/log_utils.py
google/adk/a2a/utils/__init__.py
google/adk/a2a/utils/agent_card_builder.py
google/adk/a2a/utils/agent_to_a2a.py
google/adk/agents/__init__.py
google/adk/agents/active_streaming_tool.py
google/adk/agents/agent_config.py
google/adk/agents/base_agent.py
google/adk/agents/base_agent_config.py
google/adk/agents/callback_context.py
google/adk/agents/common_configs.py
google/adk/agents/config_agent_utils.py
google/adk/agents/context_cache_config.py
google/adk/agents/invocation_context.py
google/adk/agents/langgraph_agent.py
google/adk/agents/live_request_queue.py
google/adk/agents/llm_agent.py
google/adk/agents/llm_agent_config.py
google/adk/agents/loop_agent.py
google/adk/agents/loop_agent_config.py
google/adk/agents/parallel_agent.py
google/adk/agents/parallel_agent_config.py
google/adk/agents/readonly_context.py
google/adk/agents/remote_a2a_agent.py
google/adk/agents/run_config.py
google/adk/agents/sequential_agent.py
google/adk/agents/sequential_agent_config.py
google/adk/agents/transcription_entry.py
google/adk/agents/config_schemas/AgentConfig.json
google/adk/apps/__init__.py
google/adk/apps/app.py
google/adk/apps/base_events_compactor.py
google/adk/artifacts/__init__.py
google/adk/artifacts/base_artifact_service.py
google/adk/artifacts/gcs_artifact_service.py
google/adk/artifacts/in_memory_artifact_service.py
google/adk/auth/__init__.py
google/adk/auth/auth_credential.py
google/adk/auth/auth_handler.py
google_adk-1.15.0.dist-info/entry_points.txt
google_adk-1.15.0.dist-info/licenses/LICENSE
google_adk-1.15.0.dist-info/WHEEL
google_adk-1.15.0.dist-info/METADATA
google_adk-1.15.0.dist-info/RECORD
