Metadata-Version: 2.4
Name: google-adk
Version: 1.15.0
Summary: Agent Development Kit
Author-email: Google LLC <googleapis-packages@google.com>
Requires-Python: >=3.9
Classifier: Typing :: Typed
Classifier: Intended Audience :: Developers
Classifier: Intended Audience :: Science/Research
Classifier: Programming Language :: Python
Classifier: Programming Language :: Python :: 3
Classifier: Programming Language :: Python :: 3.9
Classifier: Programming Language :: Python :: 3.10
Classifier: Programming Language :: Python :: 3.11
Classifier: Programming Language :: Python :: 3.12
Classifier: Programming Language :: Python :: 3.13
Classifier: Operating System :: OS Independent
Classifier: Topic :: Software Development :: Libraries :: Python Modules
Classifier: License :: OSI Approved :: Apache Software License
License-File: LICENSE
Requires-Dist: PyYAML>=6.0.2, <7.0.0
Requires-Dist: absolufy-imports>=0.3.1, <1.0.0
Requires-Dist: anyio>=4.9.0, <5.0.0;python_version>='3.10'
Requires-Dist: authlib>=1.5.1, <2.0.0
Requires-Dist: click>=8.1.8, <9.0.0
Requires-Dist: fastapi>=0.115.0, <1.0.0
Requires-Dist: google-api-python-client>=2.157.0, <3.0.0
Requires-Dist: google-cloud-aiplatform[agent-engines]>=1.95.1, <2.0.0
Requires-Dist: google-cloud-bigtable>=2.32.0
Requires-Dist: google-cloud-secret-manager>=2.22.0, <3.0.0
Requires-Dist: google-cloud-spanner>=3.56.0, <4.0.0
Requires-Dist: google-cloud-speech>=2.30.0, <3.0.0
Requires-Dist: google-cloud-storage>=2.18.0, <3.0.0
Requires-Dist: google-genai>=1.21.1, <1.37.0
Requires-Dist: graphviz>=0.20.2, <1.0.0
Requires-Dist: mcp>=1.8.0, <2.0.0;python_version>='3.10'
Requires-Dist: opentelemetry-api>=1.31.0, <=1.37.0
Requires-Dist: opentelemetry-exporter-gcp-logging>=1.9.0a0, <2.0.0
Requires-Dist: opentelemetry-exporter-gcp-monitoring>=1.9.0a0, <2.0.0
Requires-Dist: opentelemetry-exporter-gcp-trace>=1.9.0, <2.0.0
Requires-Dist: opentelemetry-exporter-otlp-proto-http>=1.36.0
Requires-Dist: opentelemetry-resourcedetector-gcp>=1.9.0a0, <2.0.0
Requires-Dist: opentelemetry-sdk>=1.31.0, <=1.37.0
Requires-Dist: pydantic>=2.0, <3.0.0
Requires-Dist: python-dateutil>=2.9.0.post0, <3.0.0
Requires-Dist: python-dotenv>=1.0.0, <2.0.0
Requires-Dist: requests>=2.32.4, <3.0.0
Requires-Dist: sqlalchemy>=2.0, <3.0.0
Requires-Dist: sqlalchemy-spanner>=1.14.0
Requires-Dist: starlette>=0.46.2, <1.0.0
Requires-Dist: tenacity>=8.0.0, <9.0.0
Requires-Dist: typing-extensions>=4.5, <5
Requires-Dist: tzlocal>=5.3, <6.0
Requires-Dist: uvicorn>=0.34.0, <1.0.0
Requires-Dist: watchdog>=6.0.0, <7.0.0
Requires-Dist: websockets>=15.0.1, <16.0.0
Requires-Dist: a2a-sdk>=0.3.4,<0.4.0 ; extra == "a2a" and (python_version>='3.10')
Requires-Dist: google-adk-community ; extra == "community"
Requires-Dist: flit>=3.10.0 ; extra == "dev"
Requires-Dist: isort>=6.0.0 ; extra == "dev"
Requires-Dist: mypy>=1.15.0 ; extra == "dev"
Requires-Dist: pyink>=24.10.0 ; extra == "dev"
Requires-Dist: pylint>=2.6.0 ; extra == "dev"
Requires-Dist: autodoc_pydantic ; extra == "docs"
Requires-Dist: furo ; extra == "docs"
Requires-Dist: myst-parser ; extra == "docs"
Requires-Dist: sphinx ; extra == "docs"
Requires-Dist: sphinx-autodoc-typehints ; extra == "docs"
Requires-Dist: sphinx-rtd-theme ; extra == "docs"
Requires-Dist: google-cloud-aiplatform[evaluation]>=1.100.0 ; extra == "eval"
Requires-Dist: pandas>=2.2.3 ; extra == "eval"
Requires-Dist: rouge-score>=0.1.2 ; extra == "eval"
Requires-Dist: tabulate>=0.9.0 ; extra == "eval"
Requires-Dist: anthropic>=0.43.0 ; extra == "extensions"
Requires-Dist: beautifulsoup4>=3.2.2 ; extra == "extensions"
Requires-Dist: crewai[tools] ; extra == "extensions" and (python_version>='3.10')
Requires-Dist: docker>=7.0.0 ; extra == "extensions"
Requires-Dist: kubernetes>=29.0.0 ; extra == "extensions"
Requires-Dist: langgraph>=0.2.60 ; extra == "extensions"
Requires-Dist: litellm>=1.75.5 ; extra == "extensions"
Requires-Dist: llama-index-readers-file>=0.4.0 ; extra == "extensions"
Requires-Dist: llama-index-embeddings-google-genai>=0.3.0 ; extra == "extensions"
Requires-Dist: lxml>=5.3.0 ; extra == "extensions"
Requires-Dist: toolbox-core>=0.1.0 ; extra == "extensions"
Requires-Dist: opentelemetry-instrumentation-google-genai>=0.3b0, <1.0.0 ; extra == "otel-gcp"
Requires-Dist: a2a-sdk>=0.3.0,<0.4.0 ; extra == "test" and (python_version>='3.10')
Requires-Dist: anthropic>=0.43.0 ; extra == "test"
Requires-Dist: kubernetes>=29.0.0 ; extra == "test"
Requires-Dist: langchain-community>=0.3.17 ; extra == "test"
Requires-Dist: langgraph>=0.2.60, <= 0.4.10 ; extra == "test"
Requires-Dist: litellm>=1.75.5, <2.0.0 ; extra == "test"
Requires-Dist: llama-index-readers-file>=0.4.0 ; extra == "test"
Requires-Dist: openai>=1.100.2 ; extra == "test"
Requires-Dist: pytest>=8.3.4 ; extra == "test"
Requires-Dist: pytest-asyncio>=0.25.0 ; extra == "test"
Requires-Dist: pytest-mock>=3.14.0 ; extra == "test"
Requires-Dist: pytest-xdist>=3.6.1 ; extra == "test"
Requires-Dist: python-multipart>=0.0.9 ; extra == "test"
Requires-Dist: rouge-score>=0.1.2 ; extra == "test"
Requires-Dist: tabulate>=0.9.0 ; extra == "test"
Project-URL: changelog, https://github.com/google/adk-python/blob/main/CHANGELOG.md
Project-URL: documentation, https://google.github.io/adk-docs/
Project-URL: homepage, https://google.github.io/adk-docs/
Project-URL: repository, https://github.com/google/adk-python
Provides-Extra: a2a
Provides-Extra: community
Provides-Extra: dev
Provides-Extra: docs
Provides-Extra: eval
Provides-Extra: extensions
Provides-Extra: otel-gcp
Provides-Extra: test
